pykeychain/__init__.py
pykeychain/_storage.py
pykeychain-2.0.1.dist-info/LICENSE
pykeychain-2.0.1.dist-info/METADATA
pykeychain-2.0.1.dist-info/WHEEL
pykeychain-2.0.1.dist-info/RECORD
